cify/__init__.py
cify/algorithm.py
cify/objective_function.py
cify/optimization.py
cify/position.py
cify/random.py
cify/task.py
cify/utils.py
cify/ga/__init__.py
cify/ga/crossover.py
cify/ga/ga.py
cify/ga/mutate.py
cify/ga/select.py
cify/pso/__init__.py
cify/pso/particle.py
cify/pso/pso.py
cify/pso/utils.py
cify/pso/velocity.py
cify-0.0.2.dist-info/LICENSE
cify-0.0.2.dist-info/METADATA
cify-0.0.2.dist-info/WHEEL
cify-0.0.2.dist-info/top_level.txt
cify-0.0.2.dist-info/RECORD
